furchain/__init__.py
furchain/audio/__init__.py
furchain/audio/conversion/__init__.py
furchain/audio/conversion/gpt_sovits_vc.py
furchain/audio/conversion/rvc.py
furchain/audio/conversion/sovits.py
furchain/audio/schema.py
furchain/audio/speech/__init__.py
furchain/audio/speech/chat_tts.py
furchain/audio/speech/gpt_sovits.py
furchain/audio/transcriptions/__init__.py
furchain/audio/transcriptions/funasr.py
furchain/audio/utils/__init__.py
furchain/audio/utils/audio_editor.py
furchain/audio/utils/audio_iterator.py
furchain/audio/utils/audio_separator.py
furchain/audio/utils/convert.py
furchain/audio/utils/get_format.py
furchain/audio/utils/microphone.py
furchain/audio/utils/play.py
furchain/config.py
furchain/image/__init__.py
furchain/image/captions/__init__.py
furchain/image/generation/__init__.py
furchain/image/generation/stable_diffusion_webui.py
furchain/image/schema.py
furchain/interaction/__init__.py
furchain/interaction/actions.py
furchain/interaction/schema.py
furchain/interaction/tools.py
furchain/logger.py
furchain/text/__init__.py
furchain/text/callbacks.py
furchain/text/chat_format.py
furchain/text/chat_message_history.py
furchain/text/chat_prompt_templates.py
furchain/text/grammars.py
furchain/text/llama_cpp_client.py
furchain/text/output_parsers.py
furchain/text/schema.py
furchain/utils/__init__.py
furchain/utils/broadcaster.py
furchain/utils/iterator.py
furchain-0.1.6.dist-info/METADATA
furchain-0.1.6.dist-info/WHEEL
furchain-0.1.6.dist-info/RECORD
