Metadata-Version: 2.1
Name: furchain
Version: 0.1.6
Summary: FurChain is an innovative toolkit for creating and interacting with digital personas, complete with voice cloning and role-playing capabilities. It offers a suite of tools for real-time voice manipulation, chatbot creation, and text-based RPG adventures, all while being open-source and operable offline.
Author: markyfsun
Author-email: mark@furchain.xyz
Requires-Python: >=3.10,<4.0
Classifier: Programming Language :: Python :: 3
Classifier: Programming Language :: Python :: 3.10
Classifier: Programming Language :: Python :: 3.11
Classifier: Programming Language :: Python :: 3.12
Requires-Dist: audio-separator[gpu] (>=0.13.0,<0.14.0)
Requires-Dist: azure-cognitiveservices-speech (>=1.37.0,<2.0.0)
Requires-Dist: emoji (>=2.10.1,<3.0.0)
Requires-Dist: ffmpeg-python (>=0.2.0,<0.3.0)
Requires-Dist: langchain (>=0.1.4,<0.2.0)
Requires-Dist: langchain-community (>=0.0.16,<0.0.17)
Requires-Dist: langchain-core (>=0.1.16,<0.2.0)
Requires-Dist: librosa (>=0.10.1,<0.11.0)
Requires-Dist: llama-cpp-python (>=0.2.52,<0.3.0)
Requires-Dist: openai (>=1.10.0,<2.0.0)
Requires-Dist: pyaudio (>=0.2.14,<0.3.0)
Requires-Dist: pydantic (>=2.5.3,<3.0.0)
Requires-Dist: pydub (>=0.25.1,<0.26.0)
Requires-Dist: pymongo (>=4.6.1,<5.0.0)
Requires-Dist: python-dotenv (>=1.0.1,<2.0.0)
Requires-Dist: requests (>=2.31.0,<3.0.0)
Requires-Dist: soundfile (>=0.12.1,<0.13.0)
Requires-Dist: sympy (>=1.12,<2.0)
Requires-Dist: websocket-client (>=1.7.0,<2.0.0)
Requires-Dist: websockets (>=12.0,<13.0)
Requires-Dist: webuiapi (>=0.9.9,<0.10.0)
